frame_cli/__init__.py
frame_cli/check.py
frame_cli/config.py
frame_cli/info.py
frame_cli/init.py
frame_cli/listing.py
frame_cli/logging.py
frame_cli/main.py
frame_cli/metadata.py
frame_cli/pull.py
frame_cli/push.py
frame_cli/show.py
frame_cli/update.py
frame_cli/utils.py
frame_cli/downloaders/__init__.py
frame_cli/downloaders/dlhub.py
frame_cli/downloaders/downloader.py
frame_cli/downloaders/git.py
frame_cli/downloaders/hydroshare.py
frame_cli/downloaders/zenodo.py
frame_cli/environment_managers/conda.py
frame_cli/environment_managers/environment_manager.py
frame_cli/environment_managers/julia.py
frame_cli/environment_managers/python.py
frame_cli-0.2.0.dist-info/licenses/LICENSE
frame_cli-0.2.0.dist-info/METADATA
frame_cli-0.2.0.dist-info/WHEEL
frame_cli-0.2.0.dist-info/entry_points.txt
frame_cli-0.2.0.dist-info/top_level.txt
frame_cli-0.2.0.dist-info/RECORD
