Metadata-Version: 2.4
Name: frame-cli
Version: 0.2.0
Summary: Command line interface for managing FRAME hybrid models
Author-email: Son Pham-Ba <son.phamba@epfl.ch>
License: GPL-3.0-or-later
Project-URL: repository, https://github.com/CHANGE-EPFL/frame-project-cli
Requires-Python: <3.14,>=3.10
License-File: LICENSE
Requires-Dist: gitpython~=3.1.43
Requires-Dist: pip>=25.1.1
Requires-Dist: pydantic~=2.11.4
Requires-Dist: pygithub>=2.6.1
Requires-Dist: python-dotenv~=1.0.1
Requires-Dist: pyyaml>=6.0.2
Requires-Dist: requests~=2.32.3
Requires-Dist: rich~=13.9.3
Requires-Dist: sphinx-press-theme>=0.9.1
Requires-Dist: typer~=0.15.1
Provides-Extra: dev
Requires-Dist: myst-parser>=4.0.1; extra == "dev"
Requires-Dist: pre-commit~=4.0.1; extra == "dev"
Requires-Dist: pytest~=8.1.1; extra == "dev"
Requires-Dist: pytest-cov~=5.0.0; extra == "dev"
Requires-Dist: sphinx>=8.1.3; extra == "dev"
Requires-Dist: sphinx-copybutton>=0.5.2; extra == "dev"
Requires-Dist: sphinx-press-theme>=0.9.1; extra == "dev"
Provides-Extra: test
Requires-Dist: pytest~=8.1.1; extra == "test"
Requires-Dist: pytest-cov~=5.0.0; extra == "test"
Provides-Extra: doc
Requires-Dist: myst-parser>=4.0.1; extra == "doc"
Requires-Dist: sphinx>=8.1.3; extra == "doc"
Requires-Dist: sphinx-copybutton>=0.5.2; extra == "doc"
Requires-Dist: sphinx-press-theme>=0.9.1; extra == "doc"
Dynamic: license-file
